modrover/__init__.py
modrover/exceptions.py
modrover/globals.py
modrover/learner.py
modrover/rover.py
modrover/strategies/__init__.py
modrover/strategies/backward.py
modrover/strategies/base.py
modrover/strategies/forward.py
modrover/strategies/full.py
modrover-0.2.0.dist-info/LICENSE
modrover-0.2.0.dist-info/METADATA
modrover-0.2.0.dist-info/WHEEL
modrover-0.2.0.dist-info/top_level.txt
modrover-0.2.0.dist-info/RECORD
